{"file":"Down.png","frames":{
"0":{"x":983,"y":199,"w":28,"h":31,"offX":0,"offY":0,"sourceW":28,"sourceH":31},
"1":{"x":983,"y":331,"w":19,"h":31,"offX":2,"offY":0,"sourceW":22,"sourceH":31},
"2":{"x":983,"y":166,"w":28,"h":31,"offX":0,"offY":0,"sourceW":28,"sourceH":31},
"3":{"x":983,"y":133,"w":28,"h":31,"offX":0,"offY":0,"sourceW":28,"sourceH":31},
"4":{"x":983,"y":232,"w":27,"h":31,"offX":0,"offY":0,"sourceW":28,"sourceH":31},
"5":{"x":983,"y":265,"w":27,"h":31,"offX":0,"offY":0,"sourceW":28,"sourceH":31},
"6":{"x":983,"y":100,"w":28,"h":31,"offX":0,"offY":0,"sourceW":28,"sourceH":31},
"7":{"x":983,"y":298,"w":25,"h":31,"offX":1,"offY":0,"sourceW":28,"sourceH":31},
"8":{"x":983,"y":67,"w":28,"h":31,"offX":0,"offY":0,"sourceW":28,"sourceH":31},
"9":{"x":983,"y":34,"w":28,"h":31,"offX":0,"offY":0,"sourceW":28,"sourceH":31},
"blood":{"x":851,"y":835,"w":96,"h":15,"offX":0,"offY":0,"sourceW":96,"sourceH":15},
"btn01":{"x":692,"y":797,"w":93,"h":92,"offX":0,"offY":0,"sourceW":95,"sourceH":92},
"btn02":{"x":877,"y":723,"w":93,"h":92,"offX":2,"offY":0,"sourceW":95,"sourceH":92},
"floor0":{"x":356,"y":803,"w":96,"h":16,"offX":0,"offY":0,"sourceW":96,"sourceH":16},
"floor1":{"x":258,"y":836,"w":95,"h":15,"offX":0,"offY":0,"sourceW":95,"sourceH":15},
"floor2":{"x":356,"y":821,"w":96,"h":16,"offX":0,"offY":0,"sourceW":96,"sourceH":16},
"floor3":{"x":851,"y":817,"w":96,"h":16,"offX":0,"offY":0,"sourceW":96,"sourceH":16},
"floor4":{"x":258,"y":803,"w":96,"h":31,"offX":0,"offY":1,"sourceW":96,"sourceH":32},
"help":{"x":194,"y":803,"w":62,"h":87,"offX":1,"offY":0,"sourceW":65,"sourceH":88},
"help2":{"x":787,"y":797,"w":62,"h":87,"offX":1,"offY":0,"sourceW":65,"sourceH":88},
"img_ui":{"x":1,"y":1,"w":480,"h":800,"offX":0,"offY":0,"sourceW":480,"sourceH":800},
"line":{"x":965,"y":1,"w":16,"h":385,"offX":0,"offY":0,"sourceW":16,"sourceH":385},
"Main":{"x":483,"y":1,"w":480,"h":720,"offX":0,"offY":0,"sourceW":480,"sourceH":720},
"person":{"x":983,"y":1,"w":32,"h":31,"offX":0,"offY":1,"sourceW":32,"sourceH":32},
"start1":{"x":483,"y":797,"w":207,"h":70,"offX":0,"offY":0,"sourceW":209,"sourceH":71},
"start2":{"x":1,"y":803,"w":191,"h":44,"offX":0,"offY":2,"sourceW":191,"sourceH":48},
"tittle":{"x":483,"y":723,"w":392,"h":72,"offX":0,"offY":0,"sourceW":392,"sourceH":72}}}